setup.py
emp/__init__.py
emp/cli.py
emp/commands.py
emp/constants.py
emp/logging.py
emp/utils.py
emp.egg-info/PKG-INFO
emp.egg-info/SOURCES.txt
emp.egg-info/dependency_links.txt
emp.egg-info/entry_points.txt
emp.egg-info/requires.txt
emp.egg-info/top_level.txt