Metadata-Version: 1.0
Name: emp
Version: 0.1.3
Summary: Empower your Mac with simple config files
Home-page: https://github.com/snoopython/emp
Author: snoopython
Author-email: taniguchi@ioa.s.u-tokyo.ac.jp
License: UNKNOWN
Platform: UNKNOWN
